hunify_utils/__init__.py
hunify_utils/config/__init__.py
hunify_utils/config/config.py
hunify_utils/config/errors.py
hunify_utils/config/utils.py
hunify_utils/environment/__init__.py
hunify_utils/logger/__init__.py
hunify_utils/logger/extras.py
hunify_utils/logger/formatter.py
hunify_utils/logger/handler.py
hunify_utils/logger/utils.py
hunify_utils/measurement/__init__.py
hunify_utils/measurement/timing.py
hunify_utils-1.1.1.dist-info/METADATA
hunify_utils-1.1.1.dist-info/WHEEL
hunify_utils-1.1.1.dist-info/top_level.txt
hunify_utils-1.1.1.dist-info/RECORD
