Metadata-Version: 2.1
Name: hunify-utils
Version: 1.1.1
Summary: Hunify basic utilities
Home-page: https://github.com/tom4c-hunify/hunify_utils
Author: Peter Tomek
Author-email: tomek@hunifylabs.com
Classifier: Programming Language :: Python :: 3
Classifier: License :: OSI Approved :: MIT License
Classifier: Operating System :: OS Independent
Requires-Python: >=3.6
